Workbook

Sheet Solicitud de Anticipo
G2: FORMATO V&V-02 2026
A4: SOLICITUD DE ANTICIPO PARA GASTOS DE VIAJE
C6: DÍA-MES-AÑO
A7: FECHA DE ELABORACIÓN: | C7: =TODAY()
A9: BENEFICIARIO:
A11: MONTO DEL ANTICIPO: | C11: 0 | F11: DIVISA: | G11: M.N.
A13: IMPORTE CON LETRA:
A15: AUTORIZO A V&V A QUE, EN EL CASO DE NO COMPROBAR EL GASTO EN 2 DÍAS HÁBILES A MI REGRESO, SE ME DESCUENTE.
A18: INFORMACIÓN DEL MOTIVO DEL VIAJE, ASÍ COMO A QUIEN SE DEBE CARGAR EL GASTO
A20: FECHA DEL VIAJE
A21: FECHA DE SALIDA DIA-MES-AÑO | G21: FECHA DE REGRESO DIA-MES-AÑO
C24: OFICINA | D24: CLIENTE
A25: CON CARGO A :
A27: SI ES CON CARGO A CLIENTE, INDIQUE EL NOMBRE COMPLETO DEL CLIENTE Y ASUNTO
A29: NOMBRE: | G29: NÚM DE EXPEDIENTE:
A31: ASUNTO:
A33: LUGAR:
A35: DESCRIPCIÓN DEL VIAJE:
A38: INSTRUCCIONES:
A39: 1) Recabar siempre todos los comprobantes con requisitos fiscales señalados en el Artículo 29-A del Código Fiscal de la Federación o similar.
A40: 2) Solicitar una copia de la Cédula Fiscal del cliente para cuando la soliciten los Establecimientos a los cuales se le requiera comprobante Fiscal.
A41: 3) Los comprobantes deben estar a nombre de la razón social del cliente o de la Firma, según se indique, incluído el pago de derechos, de lo contrario NO SERÁN REEMBOLSADOS.
A42: 4) Pedir que todos los consumos de alimentos realizados en las instalaciónes del Hotel en el que se hospeden se incluyan dentro de la cuenta, NO LIQUIDARLOS POR SEPARADO.
A43: 5) Los importes por taxis y/o Uber y/o servicios similares, del aeropuerto o terminal hacia el lugar de destino, los alquilados por tiempo de una ciudad a otra y, por supuesto, los automóviles rentados, deberán de rendirse con comprobantes que también reúnan requisitos fiscales.
A44: 6) En caso de alimentos erogados en teritorio nacional, sólo se reembolsarán hasta un monto de $290.00 pesos por consumo y cuando se erogen en el extranjero $20.00 USD, y deberán ser pagados con tarjeta de crédito o débito y deberá acompañar factura correspondiente.
A45: 7) Renta de automóviles, sólo se pagarán hasta un monto de $900.00 pesos diarios en territorio nacional o su equivalente en USD en el extranjero, debiendo anexar factura correspondiente.
A46: 8) En el caso de hospedaje, solo se reembolsarán hasta un monto de $2,100.00 pesos diarios o su equivalente en USD y deberán acompañar comprobante.
... A51: FIRMAS DE AUTORIZACIÓN
A53: SOLICITÓ | D53: AUTORIZACIÓN DE SOCIO | H53: REVISIÓN CONTABLE

Sheet Solicitud Reembolso
G2: FORMATO V&V-03 2026
A4: SOLICITUD DE REEMBOLSO DE GASTOS
C6: DÍA-MES-AÑO | G6: SI | H6: NO
A7: FECHA DE ELABORACIÓN: | C7: =TODAY() | E7: COMPROBANTES ANEXOS:
A9: BENEFICIARIO:
A11: MONTO DE TRANSFERENCIA: | C11: ='Detalle de Gastos'!J26 | E11: DIVISA: | F11: M.N.
A13: IMPORTE CON LETRA:
A16: INFORMACIÓN DEL MOTIVO DEL GASTO
A17: FECHA DEL VIAJE
A19: FECHA DE SALIDA DIA-MES-AÑO | G19: FECHA DE REGRESO DIA-MES-AÑO
B22: OFICINA | C22: CLIENTE | D22: EMPLEADO
A23: CON CARGO A:
A25: SI ES CON CARGO AL CLIENTE O EMPLEADO INDIQUE EL NOMBRE DEL CLIENTE O NOMBRE, NÚMERO DE EMPLEADO Y ASUNTO.
A27: NOMBRE: | G27: NUM DE EXPEDIENTE:
A29: ASUNTO:
A32: LUGAR:
A34: DESCRIPCIÓN DEL GASTO:
A37: INSTRUCCIONES:
A38: 1) Recabar siempre todos los comprobantes con requisitos fiscales señalados en el Artículo 29-A del Código Fiscal de la Federación o similar.
A39: 2) Solicitar una copia de la Cédula Fiscal del cliente para cuando la soliciten los Establecimientos a los cuales se le requiera comprobante Fiscal.
A40: 3) Los comprobantes deben estar a nombre de la razón social del cliente o de la Firma, según se indique, incluído el pago de derechos, de lo contrario NO SERÁN REEMBOLSADOS.
A41: 4) Pedir que todos los consumos de alimentos realizados en las instalaciónes del Hotel en el que se hospeden se incluyan dentro de la cuenta, NO LIQUIDARLOS POR SEPARADO.
A42: 5) Los importes por taxis y/o Uber y/o servicios similares, del aeropuerto o terminal hacia el lugar de destino, los alquilados por tiempo de una ciudad a otra y, por supuesto, los automóviles rentados, deberán de rendirse con comprobantes que también reúnan requisitos fiscales.
A43: 6) En caso de alimentos erogados en teritorio nacional, sólo se reembolsarán hasta un monto de $290.00 pesos por consumo y cuando se erogen en el extranjero $20.00 USD, y deberán ser pagados con tarjeta de crédito o débito y deberá acompañar factura correspondiente.
A44: 7) Renta de automóviles, sólo se pagarán hasta un monto de $900.00 pesos diarios en territorio nacional o su equivalente en USD en el extranjero, debiendo anexar factura correspondiente.
A45: 8) En el caso de hospedaje, solo se reembolsarán hasta un monto de $2,100.00 pesos diarios o su equivalente en USD y deberán acompañar comprobante.
... A49: FIRMAS DE AUTORIZACIÓN
A52: SOLICITÓ | D52: AUTORIZACIÓN DE SOCIO | G52: REVISIÓN CONTABLE

Sheet Comprobación y Autorización
E1: FORMATO V&V-04 2026
A3: COMPROBACIÓN Y AUTORIZACIÓN DE GASTOS DE VIAJE
A4: ANEXAR EL DETALLE DE GASTOS FORMATO V&V-05
A6: FECHA DEL VIAJE
A7: SALIDA | E7: REGRESO
A10: BENEFICIARIO:
A12: CON CARGO:
A14: ASUNTO:
A17: ANTICIPO: | B17: 0 | C17: DIVISA: | D17: 0 | E17: Nº DE TRANSF:
A19: LUGAR:
A21: DESCRIPCIÓN DEL VIAJE:
A25: GASTOS EFECTUADOS
B27: GASTOS CON IVA | C27: GASTOS SIN IVA | D27: IVA | F27: Retención o Disminución | G27: TOTAL
A28: GASTO TOTAL: | B28: ='Detalle de Gastos'!F18 | C28: ='Detalle de Gastos'!G18 | D28: ='Detalle de Gastos'!H18 | F28: ='Detalle de Gastos'!I18 | G28: ='Detalle de Gastos'!J18
C30: MENOS: | D30: ANTICIPO | G30: =B17
A32: DIFERENCIA A CARGO O DIFERENCIA A ( FAVOR ) | G32: =+G30-G28
A34: NOTA:
A35: * VER DETALLE ANEXO PARA DESGLOSE DE GASTOS REALIZADOS
A36: * VER INSTRUCCIONES EN DETALLE DE GASTOS
A37: BOLETO DE AVIÓN:
A38: (ANEXE UNA COPIA E INDIQUE EL IMPORTE DEL BOLETO DE AVIÓN SOLO EN CASO QUE V&V HAYA PAGADO EL BOLETO) $_________________.
D40: SI | E40: NO
A41: INDIQUE SI EL CLIENTE PAGÓ EL BOLETO
A43: FIRMAS DE AUTORIZACIÓN
A46: SOLICITÓ | C46: AUTORIZACIÓN DE SOCIO | F46: REVISIÓN CONTABLE

Sheet Detalle de Gastos
H2: FORMATO V&V-05 2026
A4: COMPLEMENTO DE ANEXO FORMATO V&V-02, V&V-03 Y V&V-04
A6: COMPROBACIÓN ANALÍTICA DE GASTOS
A7: TIPO DE GASTO | B7: COMPRO- BANTE ANEXO | C7: RFC | D7: CURP | E7: NOMBRE | F7: IMPORTE BASE IVA | G7: IMPORTE NO CAUSA IVA | H7: IVA | I7: RETENCIONES O DISMINUCIONES | J7: TOTAL
F8: 0 | G8: 0 | H8: =F8*16% | I8: 0 | J8: =F8+G8+H8+I8
F9: 0 | G9: 0 | H9: =F9*16% | I9: 0 | J9: =F9+G9+H9+I9
F10: 0 | G10: 0 | H10: =F10*16% | I10: 0 | J10: =F10+G10+H10+I10
F11: 0 | G11: 0 | H11: =F11*16% | I11: 0 | J11: =F11+G11+H11+I11
F12: 0 | G12: 0 | H12: =F12*16% | I12: 0 | J12: =F12+G12+H12+I12
F13: 0 | G13: 0 | H13: =F13*16% | I13: 0 | J13: =F13+G13+H13+I13
F14: 0 | G14: 0 | H14: =F14*16% | I14: 0 | J14: =F14+G14+H14+I14
F15: 0 | G15: 0 | H15: =F15*16% | I15: 0 | J15: =F15+G15+H15+I15
F16: 0 | G16: 0 | H16: =F16*16% | I16: 0 | J16: =F16+G16+H16+I16
E18: SUMAS | F18: =SUM(F8:F17) | G18: =SUM(G8:G17) | H18: =SUM(H8:H17) | I18: =SUM(I8:I15) | J18: =SUM(J8:J17)
A19: INSTRUCCIONES:
A20: Todos los comprobantes deben reunir los requisitos fiscales señalados en el Aticulo 29-A del Código Fiscal de la Federación o similar.
A21: Los comprobantes deben estar a nombre del cliente o de la Firma, según se indique, incluído el pago de derechos, de lo contrario NO SERÁN REEMBOLSADOS
A22: Considerar los montos máximos indicados en los Formatos V&V-02 y V&V-03, en los cuales se solicita anticipo o reembolso de gastos de viaje.
